{
    "audio_id": "AUDIO_00005",
    "tipo": "registro_inicial",
    "timestamp_recepcion": "2026-05-27T02:01:18.088000Z",
    "fecha_recepcion": "2026-05-27",
    "transcripcion": "Hola, me llamo Carlos Ramírez, soy productor de cacao en la zona rural del municipio de  Patalito, departamento de Ulia. Tengo una finca de tres hectáreas con variedad  trinitario y manejo el cultivo bajo sombra con árboles forestales y plátano para  proteger el suelo.",
    "evento": {
        "fecha_evento": null,
        "fecha_evento_fin": null,
        "granularidad_fecha_evento": null,
        "cultivo": "cacao",
        "variedad": "trinitario",
        "accion": null,
        "categoria_accion": null,
        "magnitudes": [
            {
                "tipo": "superficie",
                "valor": 3.0,
                "unidad": "ha",
                "unidad_original": "hectareas",
                "estado": "ok"
            }
        ],
        "problemas": [],
        "tratamientos": [],
        "partes_planta": [],
        "estado_cultivo": null,
        "espacio_agricola": null,
        "localidad": "pitalito",
        "region": null,
        "pais": null,
        "factor_climatico": [],
        "sistema_produccion": null,
        "especie_sombra": [
            "arboles_forestales",
            "platano"
        ]
    },
    "estado_procesamiento": "ok",
    "normalization_version": "1.1"
}